dbuper/__init__.py
dbuper/dbuper.py
dbuper/version.py
dbuper-1.0.4.dist-info/METADATA
dbuper-1.0.4.dist-info/WHEEL
dbuper-1.0.4.dist-info/entry_points.txt
dbuper-1.0.4.dist-info/top_level.txt
dbuper-1.0.4.dist-info/RECORD
