Metadata-Version: 2.1
Name: dbuper
Version: 1.0.4
Summary: A tool for automated database backups and scheduling.
Home-page: https://github.com/benjosiah/dbuper
Author: Josiah Ben
Author-email: benjosiah90@gmail.com
License: UNKNOWN
Platform: UNKNOWN
Classifier: Programming Language :: Python :: 3
Classifier: License :: OSI Approved :: MIT License
Classifier: Operating System :: OS Independent
Requires-Python: >=3.6
Requires-Dist: click
Requires-Dist: dropbox
Requires-Dist: boto3
Requires-Dist: pydrive2
Requires-Dist: python-crontab
Requires-Dist: setuptools
